[
  {
    "date": "Abril 17",
    "dateTime": "2023-04-17",
    "summary": "Neste dia teremos palestras sobre NFT's, introdução a blockchain, etc.",
    "timeSlots": [
      {
        "name": "Sessão de abertura",
        "description": null,
        "start": "10:30AM",
        "end": "11:00AM"
      },
      {
        "name": "Introdução aos NFT's: Aplicações práticas e riscos",
        "description": "Dra.Ana Peixoto e José Gomes",
        "start": "11:00AM",
        "end": "1:00PM"
      },
      {
        "name": "Almoço",
        "description": null,
        "start": "1:00PM",
        "end": "2:30PM"
      },
      {
        "name": "What the hell is blockchain?",
        "description": "José Peixoto",
        "start": "2:30PM",
        "end": "4:00PM"
      },
      {
        "name": "Lanche",
        "description": null,
        "start": "4:00PM",
        "end": "4:30PM"
      },
      {
        "name": "Compra de Bens atraves da Blockchain",
        "description": "Pai da Matilde",
        "start": "4:30PM",
        "end": "6:00PM"
      }
    ]
  },
  {
    "date": "Abril 18",
    "dateTime": "2023-04-18",
    "summary": "Next we spend the day talking about deceiving people with technology.",
    "timeSlots": [
      {
        "name": "Damaris Kimura",
        "description": "The invisible card reader",
        "start": "9:00AM",
        "end": "10:00AM"
      },
      {
        "name": "Ibrahim Frasch",
        "description": "Stealing fingerprints",
        "start": "10:00AM",
        "end": "11:00AM"
      },
      {
        "name": "Cathlene Burrage",
        "description": "Voting machines",
        "start": "11:00AM",
        "end": "12:00PM"
      },
      {
        "name": "Lunch",
        "description": null,
        "start": "12:00PM",
        "end": "1:00PM"
      },
      {
        "name": "Rinaldo Beynon",
        "description": "Blackhat SEO that works",
        "start": "1:00PM",
        "end": "2:00PM"
      },
      {
        "name": "Waylon Hyden",
        "description": "Turning your audience into a botnet",
        "start": "2:00PM",
        "end": "3:00PM"
      },
      {
        "name": "Giordano Sagucio",
        "description": "Fly phishing",
        "start": "3:00PM",
        "end": "4:00PM"
      }
    ]
  },
  {
    "date": "Abril 19",
    "dateTime": "2023-04-19",
    "summary": "Next we spend the day talking about deceiving people with technology.",
    "timeSlots": [
      {
        "name": "Damaris Kimura",
        "description": "The invisible card reader",
        "start": "9:00AM",
        "end": "10:00AM"
      },
      {
        "name": "Ibrahim Frasch",
        "description": "Stealing fingerprints",
        "start": "10:00AM",
        "end": "11:00AM"
      },
      {
        "name": "Cathlene Burrage",
        "description": "Voting machines",
        "start": "11:00AM",
        "end": "12:00PM"
      },
      {
        "name": "Lunch",
        "description": null,
        "start": "12:00PM",
        "end": "1:00PM"
      },
      {
        "name": "Rinaldo Beynon",
        "description": "Blackhat SEO that works",
        "start": "1:00PM",
        "end": "2:00PM"
      },
      {
        "name": "Waylon Hyden",
        "description": "Turning your audience into a botnet",
        "start": "2:00PM",
        "end": "3:00PM"
      },
      {
        "name": "Giordano Sagucio",
        "description": "Fly phishing",
        "start": "3:00PM",
        "end": "4:00PM"
      }
    ]
  }
]
